{
  "intents": [
    {
      "intent": "AddPlayerIntent",
      "slots": [
        {
          "name": "PlayerName",
          "type": "LIST_OF_PLAYER_NAMES"
        }
      ]
    },
    {
      "intent": "AddLifeIntent",
      "slots": [
        {
          "name": "PlayerName",
          "type": "LIST_OF_PLAYER_NAMES"
        },
        {
          "name": "LifeNumber",
          "type": "AMAZON.NUMBER"
        }
      ]
    },
     {
      "intent": "SubLifeIntent",
      "slots": [
        {
          "name": "PlayerName",
          "type": "LIST_OF_PLAYER_NAMES"
        },
        {
          "name": "LifeNumber",
          "type": "AMAZON.NUMBER"
        }
      ]
    },
    {
      "intent": "ResetPlayersIntent"
    },
    {
      "intent": "NewGameIntent"
    },
    {
      "intent": "TellLifeTotalsIntent"
    },
    {
      "intent": "AMAZON.HelpIntent"
    },
    {
      "intent": "AMAZON.StopIntent"
    },
    {
      "intent": "AMAZON.CancelIntent"
    }
  ]
}
